[{"id":0,"href":"/01-%E7%BC%96%E7%A8%8B%E8%AF%AD%E8%A8%80/Golang/","title":"Golang","parent":"01 编程语言","content":"知识点     语言的特点和优势 数据类型及定义 bool, string, number, 流程控制Flow control（循环for, 分支if else and switch; 错误处理defer, panic, recover, Errors） Pointers, Structs, Arrays, Slices, Range, Maps OOP(Methods and Interfaces), Stringers Type Assertions, Type switches Readers Goroutines, Channels, Buffered Channels, Select, sync.Mutex  测试和调试     单元测试 go test  MVC框架     编译、调试  go build helloWorld dlv debug   日志输出 错误处理 交叉编译 GOARCH=mips GOOS=linux go build -o test helloworld.go go tool dist list //查看GOARCH和GOOS  Webassembly    GOARCH=wasm GOOS=js go build -ldflags \u0026ldquo;-s -w\u0026rdquo; -o test.wasm helloworld.go\nNotes     By convention, the package name is the same as the last element of the import path. A name is exported if it begins with a capital letter. When importing a package, you can refer only to its exported names. Any \u0026ldquo;unexported\u0026rdquo; names are not accessible from outside the package. The type comes after the variable name. https://blog.golang.org/gos-declaration-syntax When two or more consecutive named function parameters share a type, you can omit the type from all but the last. A function can return any number of results. Go\u0026rsquo;s return values may be named. If so, they are treated as variables defined at the top of the function. The var statement declares a list of variables.A var declaration can include initializers, one per variable. If an initializer is present, the type can be omitted; the variable will take the type of the initializer. Inside a function, the := short assignment statement can be used in place of a var declaration with implicit type. Outside a function, every statement begins with a keyword (var, func, and so on) and so the := construct is not available. Go\u0026rsquo;s basic types are   bool string int int8 int16 int32 int64 uint uint8 uint16 uint32 uint64 uintptr byte // alias for uint8 rune // alias for int32 // represents a Unicode code point float32 float64 complex64 complex128  The example shows variables of several types, and also that variable declarations may be \u0026ldquo;factored\u0026rdquo; into blocks, as with import statements. The int, uint, and uintptr types are usually 32 bits wide on 32-bit systems and 64 bits wide on 64-bit systems. When you need an integer value you should use int unless you have a specific reason to use a sized or unsigned integer type.\nVariables declared without an explicit initial value are given their zero value. The zero value is: 0 for numeric types, false the boolean type, and \u0026quot;\u0026quot; (the empty string) for strings. When declaring a variable without specifying an explicit type (either by using the := syntax or var = expression syntax), the variable\u0026rsquo;s type is inferred from the value on the right hand side. Constants are declared like variables, but with the const keyword. Constants can be character, string, boolean, or numeric values. Constants cannot be declared using the := syntax. Numeric constants are high-precision values. An untyped constant takes the type needed by its context. Go has only one looping construct, the for loop. The init statement will often be a short variable declaration, and the variables declared there are visible only in the scope of the for statement. Unlike other languages like C, Java, or Javascript there are no parentheses surrounding the three components of the for statement and the braces { } are always required.   The init and post statement are optional. At that point you can drop the semicolons: C\u0026rsquo;s while is spelled for in Go. If you omit the loop condition it loops forever, so an infinite loop is compactly expressed.  Go\u0026rsquo;s if statements are like its for loops; the expression need not be surrounded by parentheses ( ) but the braces { } are required.   Like for, the if statement can start with a short statement to execute before the condition. Variables declared by the statement are only in scope until the end of the if. Variables declared inside an if short statement are also available inside any of the else blocks.  A case body in switch statement breaks automatically, unless it ends with a fallthrough statement.   Switch cases evaluate cases from top to bottom, stopping when a case succeeds. Switch without a condition is the same as switch true. This construct can be a clean way to write long if-then-else chains.  A defer statement defers the execution of a function until the surrounding function returns.   The deferred call\u0026rsquo;s arguments are evaluated immediately, but the function call is not executed until the surrounding function returns. A defer statement defers the execution of a function until the surrounding function returns. The deferred call\u0026rsquo;s arguments are evaluated immediately, but the function call is not executed until the surrounding function returns. Defer is commonly used to simplify functions that perform various clean-up actions. Deferred functions may read and assign to the returning function\u0026rsquo;s named return values.  Panic is a built-in function that stops the ordinary flow of control and begins panicking. When the function F calls panic, execution of F stops, any deferred functions in F are executed normally, and then F returns to its caller. To the caller, F then behaves like a call to panic. The process continues up the stack until all functions in the current goroutine have returned, at which point the program crashes. Panics can be initiated by invoking panic directly. They can also be caused by runtime errors, such as out-of-bounds array accesses. Recover is a built-in function that regains control of a panicking goroutine. Recover is only useful inside deferred functions. During normal execution, a call to recover will return nil and have no other effect. If the current goroutine is panicking, a call to recover will capture the value given to panic and resume normal execution. https://blog.golang.org/defer-panic-and-recover Go has pointers. A pointer holds the memory address of a variable. Unlike C, Go has no pointer arithmetic. A struct is a collection of fields. Struct fields are accessed using a dot. A struct literal denotes a newly allocated struct value by listing the values of its fields. You can list just a subset of fields by using the Name: syntax. (And the order of named fields is irrelevant.) The special prefix \u0026amp; returns a pointer to the struct value. An array\u0026rsquo;s length is part of its type, so arrays cannot be resized. This seems limiting, but don\u0026rsquo;t worry; Go provides a convenient way of working with arrays. A slice points to an array of values and also includes a length. []T is a slice with elements of type T. len(s) returns the length of slice s.   Slices can contain any type, including other slices. Slices can be re-sliced, creating a new slice value that points to the same array. Slices are created with the make function. It works by allocating a zeroed array and returning a slice that refers to that array: The zero value of a slice is nil. A nil slice has a length and capacity of 0. It is common to append new elements to a slice, and so Go provides a built-in append function. The documentation of the built-in package describes append. https://blog.golang.org/go-slices-usage-and-internals  The range form of the for loop iterates over a slice or map. When ranging over a slice, two values are returned for each iteration. The first is the index, and the second is a copy of the element at that index.   You can skip the index or value by assigning to _. If you only want the index, drop the \u0026ldquo;, value\u0026rdquo; entirely.  A map maps keys to values. Maps must be created with make before use; the nil map is empty and cannot be assigned to.   Map literals are like struct literals, but the keys are required. If the top-level type is just a type name, you can omit it from the elements of the literal. Insert or update an element in map m: m[key] = elem Retrieve an element: elem = m[key] Delete an element: delete(m, key) Test that a key is present with a two-value assignment: elem, ok = m[key] If key is in m, ok is true. If not, ok is false. If key is not in the map, then elem is the zero value for the map\u0026rsquo;s element type. Note: if elem or ok have not yet been declared you could use a short declaration form: elem, ok := m[key]  Functions are values too. They can be passed around just like other values. Function values may be used as function arguments and return values. Go functions may be closures. A closure is a function value that references variables from outside its body. The function may access and assign to the referenced variables; in this sense the function is \u0026ldquo;bound\u0026rdquo; to the variables. For example, the adder function returns a closure. Each closure is bound to its own sum variable. Go does not have classes. However, you can define methods on types. A method is a function with a special receiver argument. The receiver appears in its own argument list between the func keyword and the method name.   Remember: a method is just a function with a receiver argument. You can declare a method on non-struct types, too. You can only declare a method with a receiver whose type is defined in the same package as the method. You cannot declare a method with a receiver whose type is defined in another package (which includes the built-in types such as int).  You can declare methods with pointer receivers. This means the receiver type has the literal syntax *T for some type T. (Also, T cannot itself be a pointer such as *int.) Methods with pointer receivers can modify the value to which the receiver points (as Scale does here). Since methods often need to modify their receiver, pointer receivers are more common than value receivers. There are two reasons to use a pointer receiver. The first is so that the method can modify the value that its receiver points to. The second is to avoid copying the value on each method call. This can be more efficient if the receiver is a large struct, for example. An interface type is defined as a set of method signatures. A value of interface type can hold any value that implements those methods. A type implements an interface by implementing its methods. There is no explicit declaration of intent, no \u0026ldquo;implements\u0026rdquo; keyword. Implicit interfaces decouple the definition of an interface from its implementation, which could then appear in any package without prearrangement. Under the covers, interface values can be thought of as a tuple of a value and a concrete type: (value, type) An interface value holds a value of a specific underlying concrete type. Calling a method on an interface value executes the method of the same name on its underlying type. If the concrete value inside the interface itself is nil, the method will be called with a nil receiver. In some languages this would trigger a null pointer exception, but in Go it is common to write methods that gracefully handle being called with a nil receiver (as with the method M in this example.) Note that an interface value that holds a nil concrete value is itself non-nil. A nil interface value holds neither value nor concrete type. Calling a method on a nil interface is a run-time error because there is no type inside the interface tuple to indicate which concrete method to call. The interface type that specifies zero methods is known as the empty interface: interface{} An empty interface may hold values of any type. (Every type implements at least zero methods.) Empty interfaces are used by code that handles values of unknown type. For example, fmt.Print takes any number of arguments of type interface{}. A type assertion provides access to an interface value\u0026rsquo;s underlying concrete value. t := i.(T) This statement asserts that the interface value i holds the concrete type T and assigns the underlying T value to the variable t. If i does not hold a T, the statement will trigger a panic. To test whether an interface value holds a specific type, a type assertion can return two values: the underlying value and a boolean value that reports whether the assertion succeeded. t, ok := i.(T) If i holds a T, then t will be the underlying value and ok will be true. If not, ok will be false and t will be the zero value of type T, and no panic occurs. Note the similarity between this syntax and that of reading from a map. A type switch is a construct that permits several type assertions in series. A type switch is like a regular switch statement, but the cases in a type switch specify types (not values), and those values are compared against the type of the value held by the given interface value.   switch v := i.(type) { case T: // here v has type T case S: // here v has type S default: // no match; here v has the same type as i }  The declaration in a type switch has the same syntax as a type assertion i.(T), but the specific type T is replaced with the keyword type. This switch statement tests whether the interface value i holds a value of type T or S. In each of the T and S cases, the variable v will be of type T or S respectively and hold the value held by i. In the default case (where there is no match), the variable v is of the same interface type and value as i. 40. One of the most ubiquitous interfaces is Stringer defined by the fmt package. type Stringer interface { String() string } A Stringer is a type that can describe itself as a string. The fmt package (and many others) look for this interface to print values. 41. Go programs express error state with error values. The error type is a built-in interface similar to fmt.Stringer:\n type error interface { Error() string }  (As with fmt.Stringer, the fmt package looks for the error interface when printing values.) Functions often return an error value, and calling code should handle errors by testing whether the error equals nil.\n i, err := strconv.Atoi(\"42\") if err != nil { fmt.Printf(\"couldn't convert number: %v\\n\", err) return } fmt.Println(\"Converted integer:\", i)  A nil error denotes success; a non-nil error denotes failure. 42. A goroutine is a lightweight thread managed by the Go runtime. 43. Channels are a typed conduit through which you can send and receive values with the channel operator, \u0026lt;-. ch \u0026lt;- v // Send v to channel ch. v := \u0026lt;-ch // Receive from ch, and // assign value to v.(The data flows in the direction of the arrow.) Like maps and slices, channels must be created before use: ch := make(chan int) By default, sends and receives block until the other side is ready. This allows goroutines to synchronize without explicit locks or condition variables. 44. Channels can be buffered. Provide the buffer length as the second argument to make to initialize a buffered channel: ch := make(chan int, 100) Sends to a buffered channel block only when the buffer is full. Receives block when the buffer is empty. 45. A sender can close a channel to indicate that no more values will be sent. Receivers can test whether a channel has been closed by assigning a second parameter to the receive expression: after v, ok := \u0026lt;-ch ok is false if there are no more values to receive and the channel is closed. The loop for i := range c receives values from the channel repeatedly until it is closed. Note: Only the sender should close a channel, never the receiver. Sending on a closed channel will cause a panic. Another note: Channels aren\u0026rsquo;t like files; you don\u0026rsquo;t usually need to close them. Closing is only necessary when the receiver must be told there are no more values coming, such as to terminate a range loop. 46. The select statement lets a goroutine wait on multiple communication operations. A select blocks until one of its cases can run, then it executes that case. It chooses one at random if multiple are ready. 47. The default case in a select is run if no other case is ready. Use a default case to try a send or receive without blocking:\n select { case i :=  We\u0026rsquo;ve seen how channels are great for communication among goroutines. But what if we don\u0026rsquo;t need communication? What if we just want to make sure only one goroutine can access a variable at a time to avoid conflicts? This concept is called mutual exclusion, and the conventional name for the data structure that provides it is mutex. Go\u0026rsquo;s standard library provides mutual exclusion with sync.Mutex and its two methods: Lock Unlock We can define a block of code to be executed in mutual exclusion by surrounding it with a call to Lock and Unlock as shown on the Inc method. We can also use defer to ensure the mutex will be unlocked as in the Value method.   常见问题及解答     Q: import package时，包的前面用下划线的作用？   import ( \"database/sql\" \"fmt\" _ \"github.com/go-sql-driver/mysql\" )  A: 执行包的初始化。\nGo的变量声明为什么把类型放在变量名之后？ https://blog.golang.org/gos-declaration-syntax  "},{"id":1,"href":"/01-%E7%BC%96%E7%A8%8B%E8%AF%AD%E8%A8%80/Markdown/","title":"Markdown","parent":"01 编程语言","content":"Markdown    "},{"id":2,"href":"/01-%E7%BC%96%E7%A8%8B%E8%AF%AD%E8%A8%80/Python/","title":"Python","parent":"01 编程语言","content":"Python命令    ###启动简易Web服务器\npython3 -m http.server 8080 "},{"id":3,"href":"/01-%E7%BC%96%E7%A8%8B%E8%AF%AD%E8%A8%80/Rust/","title":"Rust","parent":"01 编程语言","content":"Rust    Installing rustup    curl \u0026ndash;proto \u0026lsquo;=https\u0026rsquo; \u0026ndash;tlsv1.2 -sSf https://sh.rustup.rs | sh\nInstalling rust-src component    rustup component add rust-src\ncargo install xargo\nrustup toolchain install nightly rustup default stable\nrustup update\nrustup target add x86_64-unknown-linux-musl rustup target add mips-unknown-linux-musl rustup target add arm-unknown-linux-musleabi rustup target add x86_64-apple-darwin\nInstalling cross toolschain    brew install musl-cross \u0026ndash;help \u0026ndash;with-arm \u0026ndash;with-mips\n.cargo/config    [target.x86_64-unknown-linux-musl] linker=\u0026ldquo;x86_64-linux-musl-gcc\u0026rdquo;\n[target.mips-unknown-linux-musl] linker=\u0026ldquo;mips-linux-musl-gcc\u0026rdquo; rustflags = [\u0026quot;-C\u0026quot;, \u0026ldquo;target-feature=+crt-static\u0026rdquo;, \u0026ldquo;-C\u0026rdquo;, \u0026ldquo;link-arg=-lgcc\u0026rdquo;]\n[target.arm-unknown-linux-musleabi] linker=\u0026ldquo;arm-linux-musleabi-gcc\u0026rdquo;\nCreating a new Cargo project    xargo init rust\nBuilding a project    xargo build \u0026ndash;verbose xargo run \u0026ndash;verbose\nxargo build \u0026ndash;target x86_64-unknown-linux-musl \u0026ndash;release \u0026ndash;verbose xargo build \u0026ndash;target mips-unknown-linux-musl \u0026ndash;release \u0026ndash;verbose xargo build \u0026ndash;target arm-unknown-linux-musleabi \u0026ndash;release \u0026ndash;verbose xargo build \u0026ndash;target x86_64-apple-darwin \u0026ndash;release \u0026ndash;verbose\nwasm-pack    curl https://rustwasm.github.io/wasm-pack/installer/init.sh -sSf | sh cargo install cargo-generate\n#Clone the project template with this command: cargo generate \u0026ndash;git https://github.com/rustwasm/wasm-pack-template wasm-pack login wasm-pack build wasm-pack publish\n"},{"id":4,"href":"/02-%E5%BC%80%E5%8F%91%E5%B7%A5%E5%85%B7/Flutter/","title":"Flutter","parent":"02 开发工具","content":"Installing Flutter    export PUB_HOSTED_URL=https://pub.flutter-io.cn export FLUTTER_STORAGE_BASE_URL=https://storage.flutter-io.cn git clone -b dev https://github.com/flutter/flutter.git export PATH=\u0026quot;$PWD/flutter/bin:$PATH\u0026quot; cd ./flutter flutter doctor\nCreate a Dart package    flutter create \u0026ndash;template=package package-name\nOpening a project in Xcode    open ios/Runner.xcworkspace\nget android sha1    keytool -list -v -keystore \u0026ldquo;./debug.keystore\u0026rdquo; -alias androiddebugkey -storepass android -keypass android\nMake release    keytool -genkey -v -keystore ~/key.jks -keyalg RSA -keysize 2048 -validity 10000 -alias key\nflutter build appbundle flutter build appbundle \u0026ndash;target-platform android-arm,android-arm64,android-x64 flutter build apk \u0026ndash;target-platform android-arm,android-arm64,android-x64 \u0026ndash;split-per-abi flutter build apk \u0026ndash;target-platform android-arm,android-arm64,android-x64\nflutter build web\n    could not download from dl.google.com  修改下面2个文件 your_flutter_sdk/packages/flutter_tools/gradle/flutter.gradle and your_app_project/android/build.gradle\nrepositories {  // google() // jcenter() maven{ url \u0026lsquo;https://maven.aliyun.com/repository/google' } maven{ url \u0026lsquo;https://maven.aliyun.com/repository/jcenter' } maven{url \u0026lsquo;http://maven.aliyun.com/nexus/content/groups/public'}\n}  "},{"id":5,"href":"/02-%E5%BC%80%E5%8F%91%E5%B7%A5%E5%85%B7/Git/","title":"Git","parent":"02 开发工具","content":"多人多项目多版本Git使用要求     每个人一个分支 每个人一个项目分支 每天update trunk只用来保持最新代码 发布的时候打tag 每次提交必须写comment  初始化    git init  分支    Branch git branch mybranch git checkout mybranch\n工作场景切换    git stash git pull git stash pop\n补丁    Patch git diff master \u0026gt; patch1 git apply patch1 (—stat —check)\n合并    Merge from dev to mybranch git merge dev\n回滚    git reset —hard HEAD^\n查看某次commit的内容    git show commit-id\n根据commit log查找    git log \u0026ndash;grep=xxx\n根据Author查找    git log \u0026ndash;author=xxx\n###svn缺点\n 严重依赖网络 移动文件夹 冲突强制解决  "},{"id":6,"href":"/06-%E6%93%8D%E4%BD%9C%E7%B3%BB%E7%BB%9F/Tcpdump/","title":"Tcpdump","parent":"06 操作系统","content":"Monitor HTTP traffic including request and response headers and message body sudo tcpdump -i 6 -A -s 0 \u0026lsquo;tcp port 8080 and (((ip[2:2] - ((ip[0]\u0026amp;0xf)\u0026laquo;2)) - ((tcp[12]\u0026amp;0xf0)\u0026raquo;2)) != 0)\u0026rsquo; -n\n"},{"id":7,"href":"/07-%E5%B5%8C%E5%85%A5%E5%BC%8F/Busybox/","title":"Busybox","parent":"07 嵌入式","content":"Busybox    make menuconfig make\n1.22.1    Working Dir: /mnt/hgfs/Woody/Desktop/LHQ/18_MyCode/2440/busybox-1.22.1 Cross Compiler gcc 4.4.3\n1.2.0 for QQ2440    Working Dir: /mnt/hgfs/Woody/Desktop/LHQ/18_MyCode/2440/busybox-1.2.0\nCross Compiler arm-linux-gnueabi-gcc 4.7 arm-linux-gcc 3.4.1\nmknod ./dev/console c 5 1 mknod ./dev/null c 1 3\ncan\u0026rsquo;t open /dev/tty3: No such file or directory can\u0026rsquo;t open /dev/tty2: No such file or directory can\u0026rsquo;t open /dev/tty4: No such file or directory\n解决办法：\nln -sf ./dev/null ./dev/tty2 ln -sf ./dev/null ./dev/tty3 ln -sf ./dev/null ./dev/tty4\n"},{"id":8,"href":"/07-%E5%B5%8C%E5%85%A5%E5%BC%8F/Openwrt/","title":"Openwrt","parent":"07 嵌入式","content":"工作目录：Ubuntu64虚拟机 /home/woody/LHQ/src/openwrt/openwrt.git.19.07     开启FPU Emulator\ngo hardfloat\ngo softfloat\nhelloclang /lib/ld-musl-mips.so.1 helloclang_static\nhellorust /lib/ld-musl-mips.so.1\n不开启FPU Emulator go hardfloat Illegal instruction\ngo softfloat\nhelloclang /lib/ld-musl-mips.so.1 helloclang_static\nhellorust /lib/ld-musl-mips.so.1 hellorust_satic\n 工作目录：Ubuntu32虚拟机 /home/woody/LHQ/src/openwrt.git     硬件改造：    http://wiki.openwrt.org/toh/tp-link/tl-wr1043nd http://www.rs-online.com/designspark/electronics/blog/hacking-the-tp-link-tl-wr703n 打开jtag http://www.devttys0.com/2014/02/re-enabling-jtag-and-debugging-the-wrt120n/ 不标准jtag http://wiki.openwrt.org/toh/tp-link/tl-wr841nd\njtag: http://wiki.openwrt.org/doc/hardware/port.jtag\n在电路设计时，JTAG口的TCK要加3.3V上拉。上拉电阻值取4.7K。另外，要考虑到在成品阶段(此时已不需要通过JTAG编程)，将TCK.TMS.TDI引脚接地，这样更能提高系统的抗干扰能力，对于提高系统的稳定性是非常主要的。\n WR1041N 硬件信息    W1 wlan C0:61:18:3C:35:96 br-lan C0:61:18:3C:35:97\nW2 EC:17:2F:46:70:E6 EC:17:2F:46:70:E7    定制目标 Features      16M Firmware\n  mtd writeable\n  Hacked USB support ext4, vfat, ntfs-3g filesystem support cp936\n  Modules luci\n  Samba Minidlna tftp\nRsync Transmission GoAgent\nWifidog nodogsplash\nutils hdparm fdisk git\n 操作步骤     OpenWrt source repository downloads  GIT\nThe recommended way of checking out the OpenWrt source code is cloning the Git repository using one of the following commands:\ntrunk (main development tree)\n Main repository  git clone git://git.openwrt.org/openwrt.git\n12.09 branch (Attitude Adjustment)\n Main repository  git clone git://git.openwrt.org/12.09/openwrt.git\n Packages feed  git clone git://git.openwrt.org/12.09/packages.git\n持续更新    On branch 16m: git stash git checkout master git pull git checkout 16m git merge master git stash pop\n Compile OpenWrt ./scripts/feeds update -a ./scripts/feeds install -a make menuconfig make V=s\nCompile packages make package/xxx/compile\n  Install OpenWrt into box sysupgrade -n openwrt.bin\n  First login telnet 192.168.1.1 passwd\n  Basic Configuration /etc/config/network config interface \u0026lsquo;lan\u0026rsquo; option ifname \u0026lsquo;eth0.1\u0026rsquo; option force_link \u0026lsquo;1\u0026rsquo; option type \u0026lsquo;bridge\u0026rsquo; option proto \u0026lsquo;static\u0026rsquo; option ipaddr \u0026lsquo;10.0.0.1\u0026rsquo; option netmask \u0026lsquo;255.255.255.0\u0026rsquo; option ip6assign \u0026lsquo;60\u0026rsquo;\n  config interface \u0026lsquo;wwan\u0026rsquo; option proto \u0026lsquo;dhcp\u0026rsquo;\n/etc/config/wireless config wifi-device radio0 option type mac80211 option channel 11 option hwmode 11g option path \u0026lsquo;platform/ar934x_wmac\u0026rsquo; option htmode HT20 # REMOVE THIS LINE TO ENABLE WIFI: option disabled 0 option country \u0026lsquo;CN\u0026rsquo;\nconfig wifi-iface option device radio0 option network wwan option mode sta option ssid \u0026lsquo;TP-LINK_2C94F0\u0026rsquo; option bssid \u0026lsquo;E0:05:C5:2C:94:F0\u0026rsquo; option encryption \u0026lsquo;psk2\u0026rsquo; option key \u0026lsquo;88888086\u0026rsquo;\nconfig wifi-iface option device radio0 option network lan option mode ap option ssid OpenWrt option encryption none\n/etc/config/firewall config zone option name wan list network \u0026lsquo;wan\u0026rsquo; list network \u0026lsquo;wan6\u0026rsquo; list network \u0026lsquo;wwan\u0026rsquo; option input REJECT option output ACCEPT option forward REJECT option masq 1 option mtu_fix 1\n Install Packages opkg update opkg install xxxx.ipk\n  Install wifidog /etc/wifidog.conf\n  AuthServer { Hostname p1.com Path / }\nRunning Wifidog for the first time\nRun Wifidog with the following switches:\nwifidog -f -d 7 -f means to run in foreground (do not become a background daemon) -d 7 increases debug output level to the maximum\n??? wifidog不能自动启动的问题：延迟10s再启动 sleep 10\n 修改固件包的默认配置 ./package/base-files/files\n/etc/config/wireless /etc/banner\n/package/network/services/samba36/files/smb.conf.template\n  增加自己的文件到固件包 ./package/base-files/files /app/goagent/local /backup/config.tar.gz\n  支持cp936 修改 ./package/kernel/linux/modules/nls.mk 内核 make kernel_menuconfig\n  usb支持\n  ./target/linux/ar71xx/files/arch/mips/ath79/mach-tl-wr1041n-v2.c 增加以下内容 include \u0026ldquo;dev-usb.h\u0026rdquo;\nstatic void __init tl_wr1041nv2_setup(void) { u8 *mac = (u8 *) KSEG1ADDR(0x1f01fc00); u8 *ee = (u8 *) KSEG1ADDR(0x1fff1000);\n ath79_register_usb(); ath79_register_m25p80(\u0026amp;tl_wr1041nv2_flash_data);  auto mount : /etc/config/fstab anno_mount\nmake menuconfig base system -\u0026gt; block-mount kernel modules -\u0026gt; block devices -\u0026gt; kmod-scsi- -\u0026gt; filesystems -\u0026gt; -\u0026gt; Native Language Support -\u0026gt; cp437, iso8859-1, utf8 -\u0026gt; USB Support -\u0026gt;\n安装GoAgent  安装依赖的软件包\n  opkg install libopenssl\n  opkg install python\n  opkg install pyopenssl python-openssl\n  下载goagent并将local目录上传到openwrt\nFlash由4M变成8M（或16M）  //———— Ignored Start ./tools/firmware-utils/src/mktplinkfw.c @@ -362,7 +362,7 @@ static struct board_info boards[] = { .id = \u0026ldquo;TL-WR1041Nv2\u0026rdquo;, .hw_id = HWID_TL_WR1041N_V2, .hw_rev = 1,\n   .layout_id = \u0026quot;4Mlzma\u0026quot;,       .layout_id = \u0026quot;16Mlzma\u0026quot;, }    // ——— Ignored End\n./target/linux/ar71xx/image/Makefile define Device/tl-wr1041n-v2 $(Device/tplink-16mlzma) BOARDNAME := TL-WR1041N-v2 DEVICE_PROFILE := TLWR1041 TPLINK_HWID := 0x10410002 endef\n否则出现如下错误: [mktplinkfw] kernel length aligned to 914864 [mktplinkfw] *** error: images are too big make[3]: [install] Error 255 (ignored)\n在openwrt中不能更新uboot时，需要做如下修改： ./target/linux/ar71xx/files/drivers/mtd/tplinkpart.c parts[0].mask_flags = MTD_WRITEABLE; //去除本行\nQ\u0026amp;A      编译ushare的依赖库libdlna时找不到libavformat？先编译ffmpeg no format arguments [-Werror=format-security] PKG_CHECK_FORMAT_SECURITY:=0\n  如何默认打开无线？修改 ./package/kernel/mac80211/files/lib/wifi/mac80211.sh\n  warning: inline function \u0026lsquo;start_log\u0026rsquo; declared but never defined -fgnu89-inline\n  "},{"id":9,"href":"/07-%E5%B5%8C%E5%85%A5%E5%BC%8F/uboot/","title":"Uboot","parent":"07 嵌入式","content":"U-Boot    工作目录：Ubuntu32 /home/woody/LHQ/src/u-boot/2014.07\nReady-to-use binaries of ELDK v5.5 are available on our FTP server in the ftp://ftp.denx.de/pub/eldk/5.5/ directory.\nARM source /opt/eldk-5.5/armv4t/environment-setup-armv4t-linux-gnueabi make O=/home/woody/LHQ/src/build/uboot/2016.02.arm4vt smdk2410_config all\nmake O=/home/woody/LHQ/src/build/uboot/2016.08.arm4vt smdk2410_config all Sandbox\nmake O=/home/woody/LHQ/src/build/uboot/2015.07.sandbox sandbox_config all NO_SDL=1 ./u-boot\n2016.05    1.1.6    arm-linux-gcc 3.4.1 @Ubuntu\nmake 100ask24x0_config make\n"},{"id":10,"href":"/08-%E8%99%9A%E6%8B%9F%E5%8C%96/Docker/","title":"Docker","parent":"08 虚拟化","content":"Docker    "},{"id":11,"href":"/10-%E5%BC%80%E5%8F%91%E8%B5%84%E6%96%99/%E5%9B%BE%E7%89%87%E5%B0%BA%E5%AF%B8/","title":"图片尺寸","parent":"10 开发资料","content":"ipad air 2 flutter: queryData.devicePixelRatio:2.0 flutter: queryData.size.width:768.0 flutter: queryData.size.height:1024.0 flutter: widthPixel:1536.0 flutter: heightPixel:2048.0 flutter: queryData.textScaleFactor:1.0\niphone 5 flutter: queryData.devicePixelRatio:2.0 flutter: queryData.size.width:320.0 flutter: queryData.size.height:568.0 flutter: widthPixel:640.0 flutter: heightPixel:1136.0 flutter: queryData.textScaleFactor:1.0 flutter: Running on iPhone5,2\nicon图标尺寸：\ndrawable-hdpi-icon 7272 drawable-ldpi-icon 3636 drawable-mdpi-icon 4848 drawable-xhdpi-icon 9696 drawable-xxhdpi-icon 144144 drawable-xxxhdpi-icon 192192 启动页：\n横屏 高×宽\ndrawable-land-hdpi-screen 480800 drawable-land-ldpi-screen 200320 drawable-land-mdpi-screen 320480 drawable-land-xhdpi-screen 7201280 drawable-land-xxhdpi-screen 9601600 drawable-land-xxxhdpi-screen 12801920 竖屏 高×宽\ndrawable-port-hdpi-screen 800480 drawable-port-ldpi-screen 320200 drawable-port-mdpi-screen 480320 drawable-port-xhdpi-screen 1280720 drawable-port-xxhdpi-screen 1600960 drawable-port-xxxhdpi-screen 19201280\n1.3屏幕密度 每英寸像素数 手机可以有相同的分辨率，但屏幕尺寸可以不相同， Diagonal pixel表示对角线的像素值(=)，DPI=933/3.7=252 Android将实际的屏幕密度分为四个通用尺寸(low，medium，high，and extra high) 一般情况下的普通屏幕：ldpi是120dpi，mdpi是160dpi，hdpi是240dpi，xhdpi是320dpi\n作者：OzanShareing 链接：https://www.jianshu.com/p/8672bb3f98e9 来源：简书 著作权归作者所有。商业转载请联系作者获得授权，非商业转载请注明出处。\nios\n 桌面图标 (app icon)   iPhonex/8/7/6 plus(@3x) : 180 x 180\n iPhone8/7/6s/6/5s/5/4s/4(@2x) : 120 x 120\n启动图片 (launch image)   iPhoen5s/5(@2x) : 640 x 1136\n iPhoen4s/4(@2x) : 640 x 960\n iPhone7/6/iPhonex/8/7/6 plus 建议使用 launch file 或 storyboard ；\n  如果依然想使用图片，尺寸数值为：\n iPhone 8/7/6(@2x) : 750 x 1334\n iPhone 8/7/6 plus (@3x) : 1242 x 2208\n iPhone x/11/11 pro (@3x) : 1125 x 2436\n系统搜索框图标 (Spotlight search results icon)   iPhonex/8/7/6plus(@3x) : 120 x 120\n iPhone8/7/6s/6/5s/5/4s/4(@2x) : 80 x 80\n系统设置图标 (Settings icon)   iPhonex/8/7/6 plus(@3x) : 87 x 87\n iPhone8/7/6s/6/5s/5/4s/4(@2x) : 58 x 58\n比较特殊的是App Store:1024x1024 ———————————————— 版权声明：本文为CSDN博主「石虎132」的原创文章，遵循 CC 4.0 BY-SA 版权协议，转载请附上原文出处链接及本声明。 原文链接：https://blog.csdn.net/shihuboke/article/details/79360428  "},{"id":12,"href":"/20-%E8%8B%B1%E8%AF%AD%E5%AD%A6%E4%B9%A0/english_level/","title":"English Level","parent":"20 英语学习","content":"Level 1：赖世雄音标； 赖世雄美语从头学（词汇量初上730，初下631，中上1067，中下1133）； English Through Pictures（词汇量Book I 200, Book II 500, Book III 1000）; Level 2：ESLPOD 6 Books； Word by Word 4500词 Level 3：美语发音视频 Level 4：开口模仿流利说 Level 5：系统模仿期 走遍美国 Level 6：赖世雄语法\n以听说为目标（文盲英语） 尽早发现和纠正错误，不要重复自己的错误（社会化） 不断激励自己（闯关）\n第一阶段：辨音（单词、短语） 目标：看到不认识的单词可以准确的读出来； 听到不认识的单子可以准确的拼出来 方法：a. 音标练习3个月，达到听准、念准的目标 b. 自然拼读1个月，熟悉发音规律\n第二阶段：语感、节奏（句子） 目标： 可以顺畅的大声朗读新材料，掌握断句、节奏、语调、语气，没有明显的口音 方法：a. 发音训练3个月 b. 大量的听和阅读 c. 经典儿歌和英文歌曲\nhttp://www.audiofilemagazine.com/\nhttp://www.bego.cc/u/1126724/1945064 http://www.ctfile.com/shared/folder_1658549_c25e7b66/\nhttp://cfsxhdkd.blog.163.com/blog/static/625374201292410460740/ http://www.ctfile.com/shared/folder_1658549_c25e7b66/ http://blog.sina.com.cn/u/1996491363\nhttp://www.openculture.com/ http://successfulenglish.com/\n1999: Holes by Louis Sachar (Publisher: Frances Foster) This is an adventure and mystery story involving a group of boys being made to dig holes as punishment. They eventually find out the real reason for the holes they dig.\n1994: The Giver by Lois Lowry (Publisher: Houghton) This is a science fiction story set in the future about a world that has eliminated (gotten rid of; no longer have) pain and suffering. However, one person is selected to keep the memories for this society, and it is not an easy job, especially for a young boy.\n1992: Shiloh by Phyllis Reynolds Naylor (Publisher: Atheneum) This is a story about a boy who wants a dog very badly, and finds one that has been poorly treated by its owner. He wants to do the right thing. Should he give it back or keep it?\n1984: Dear Mr. Henshaw by Beverly Cleary (Publisher: Morrow) This is a book in the form of letters written by a boy to an author of children’s books. The boy moves to a new town and his thoughts and difficulties about adjusting to his new family and school situation is told in these letters.\n1961: Island of the Blue Dolphins by Scott O’Dell (Publisher: Houghton) A young woman and her brother are the only survivors (remaining people living) left on an island. The young woman must find a way to live. This book is based on a true story.\nNewbery Medal Winners, 1922 - Present\n2015: The Crossover by Kwame Alexander (Houghton Mifflin Harcourt) 2014: Flora \u0026amp; Ulysses: The Illuminated Adventures by Kate DiCamillo (Candlewick Press) 2013: The One and Only Ivan by Katherine Applegate (HarperCollins Children\u0026rsquo;s Books) 2012: Dead End in Norvelt by Jack Gantos (Farrar Straus Giroux) 2011: Moon over Manifest by Clare Vanderpool (Delacorte Press, an imprint of Random House Children\u0026rsquo;s Books) 2010: When You Reach Me by Rebecca Stead (Wendy Lamb Books, an imprint of Random House Children\u0026rsquo;s Books) 2009: The Graveyard Book by Neil Gaiman, illus. by Dave McKean (HarperCollins) 2008: Good Masters! Sweet Ladies! Voices from a Medieval Village by Laura Amy Schlitz (Candlewick) 2007: The Higher Power of Lucky by Susan Patron, illus. by Matt Phelan (Simon \u0026amp; Schuster/Richard Jackson) 2006: Criss Cross by Lynne Rae Perkins (Greenwillow Books/HarperCollins) 2005: Kira-Kira by Cynthia Kadohata (Atheneum Books for Young Readers/Simon \u0026amp; Schuster) 2004: The Tale of Despereaux: Being the Story of a Mouse, a Princess, Some Soup, and a Spool of Thread by Kate DiCamillo (Candlewick Press) 2003: Crispin: The Cross of Lead by Avi (Hyperion Books for Children) 2002: A Single Shard by Linda Sue Park(Clarion Books/Houghton Mifflin) 2001: A Year Down Yonder by Richard Peck (Dial) 2000: Bud, Not Buddy by Christopher Paul Curtis (Delacorte) 1999: Holes by Louis Sachar (Frances Foster) 1998: Out of the Dust by Karen Hesse (Scholastic) 1997: The View from Saturday by E.L. Konigsburg (Jean Karl/Atheneum) 1996: The Midwife\u0026rsquo;s Apprentice by Karen Cushman (Clarion) 1995: Walk Two Moons by Sharon Creech (HarperCollins) 1994: The Giver by Lois Lowry(Houghton) 1993: Missing May by Cynthia Rylant (Jackson/Orchard) 1992: Shiloh by Phyllis Reynolds Naylor (Atheneum) 1991: Maniac Magee by Jerry Spinelli (Little, Brown) 1990: Number the Stars by Lois Lowry (Houghton) 1989: Joyful Noise: Poems for Two Voices by Paul Fleischman (Harper) 1988: Lincoln: A Photobiography by Russell Freedman (Clarion) 1987: The Whipping Boy by Sid Fleischman (Greenwillow) 1986: Sarah, Plain and Tall by Patricia MacLachlan (Harper) 1985: The Hero and the Crown by Robin McKinley (Greenwillow) 1984: Dear Mr. Henshaw by Beverly Cleary (Morrow) 1983: Dicey\u0026rsquo;s Song by Cynthia Voigt (Atheneum) 1982: A Visit to William Blake\u0026rsquo;s Inn: Poems for Innocent and Experienced Travelers by Nancy Willard (Harcourt) 1981: Jacob Have I Loved by Katherine Paterson (Crowell) 1980: A Gathering of Days: A New England Girl\u0026rsquo;s Journal, 1830-1832 by Joan W. Blos (Scribner) 1979: The Westing Game by Ellen Raskin (Dutton) 1978: Bridge to Terabithia by Katherine Paterson (Crowell) 1977: Roll of Thunder, Hear My Cry by Mildred D. Taylor (Dial) 1976: The Grey King by Susan Cooper (McElderry/Atheneum) 1975: M. C. Higgins, the Great by Virginia Hamilton (Macmillan) 1974: The Slave Dancer by Paula Fox (Bradbury) 1973: Julie of the Wolves by Jean Craighead George (Harper) 1972: Mrs. Frisby and the Rats of NIMH by Robert C. O\u0026rsquo;Brien (Atheneum) 1971: Summer of the Swans by Betsy Byars (Viking) 1970: Sounder by William H. Armstrong (Harper) 1969: The High King by Lloyd Alexander (Holt) 1968: From the Mixed-Up Files of Mrs. Basil E. Frankweiler by E.L. Konigsburg (Atheneum) 1967: Up a Road Slowly by Irene Hunt (Follett) 1966: I, Juan de Pareja by Elizabeth Borton de Trevino (Farrar) 1965: Shadow of a Bull by Maia Wojciechowska (Atheneum) 1964: It\u0026rsquo;s Like This, Cat by Emily Neville (Harper) 1963: A Wrinkle in Time by Madeleine L\u0026rsquo;Engle (Farrar) 1962: The Bronze Bow by Elizabeth George Speare (Houghton) 1961: Island of the Blue Dolphins by Scott O\u0026rsquo;Dell (Houghton) 1960: Onion John by Joseph Krumgold (Crowell) 1959: The Witch of Blackbird Pond by Elizabeth George Speare (Houghton) 1958: Rifles for Watie by Harold Keith (Crowell) 1957: Miracles on Maple Hill by Virginia Sorensen (Harcourt) 1956: Carry On, Mr. Bowditch by Jean Lee Latham (Houghton) 1955: The Wheel on the School by Meindert DeJong (Harper) 1954: \u0026hellip;And Now Miguel by Joseph Krumgold (Crowell) 1953: Secret of the Andes by Ann Nolan Clark (Viking) 1952: Ginger Pye by Eleanor Estes (Harcourt) 1951: Amos Fortune, Free Man by Elizabeth Yates (Dutton) 1950: The Door in the Wall by Marguerite de Angeli (Doubleday) 1949: King of the Wind by Marguerite Henry (Rand McNally) 1948: The Twenty-One Balloons by William Pène du Bois (Viking) 1947: Miss Hickory by Carolyn Sherwin Bailey (Viking) 1946: Strawberry Girl by Lois Lenski (Lippincott) 1945: Rabbit Hill by Robert Lawson (Viking) 1944: Johnny Tremain by Esther Forbes (Houghton) 1943: Adam of the Road by Elizabeth Janet Gray (Viking) 1942: The Matchlock Gun by Walter Edmonds (Dodd) 1941: Call It Courage by Armstrong Sperry (Macmillan) 1940: Daniel Boone by James Daugherty (Viking) 1939: Thimble Summer by Elizabeth Enright (Rinehart) 1938: The White Stag by Kate Seredy (Viking) 1937: Roller Skates by Ruth Sawyer (Viking) 1936: Caddie Woodlawn by Carol Ryrie Brink (Macmillan) 1935: Dobry by Monica Shannon (Viking) 1934: Invincible Louisa: The Story of the Author of Little Women by Cornelia Meigs (Little, Brown) 1933: Young Fu of the Upper Yangtze by Elizabeth Lewis (Winston) 1932: Waterless Mountain by Laura Adams Armer (Longmans) 1931: The Cat Who Went to Heaven by Elizabeth Coatsworth (Macmillan) 1930: Hitty, Her First Hundred Years by Rachel Field (Macmillan) 1929: The Trumpeter of Krakow by Eric P. Kelly (Macmillan) 1928: Gay Neck, the Story of a Pigeon by Dhan Gopal Mukerji (Dutton) 1927: Smoky, the Cowhorse by Will James (Scribner) 1926: Shen of the Sea by Arthur Bowie Chrisman (Dutton) 1925: Tales from Silver Lands by Charles Finger (Doubleday) 1924: The Dark Frigate by Charles Hawes (Little, Brown) 1923: The Voyages of Doctor Dolittle by Hugh Lofting (Stokes) 1922: The Story of Mankind by Hendrik Willem van Loon (Liveright)\n下面的是按Lexile阅读难度级别列出的纽奖Medal 和 Honor 书（作品截至2010年）。Lexile 的难度分级标准只有两个：词汇和句子长度。所以有的时候Lexile也不是很靠谱，不过可以做大致参考。\n其中我用红色标注的是部分出现在下列一个或几个儿童文学推荐书单里的所谓经典：\n Classic Club Children\u0026rsquo;s Catalog Junior Great Books Library of America Paideia Books and Teen-age Reader Enjoy！  Newbery book - sorted by lexile\tlexile #\tYear\tAward ABC Bunny by Wanda Gág\t220\t1934\tHonor Frog and Toad Together by Arnold Lobel\t330\t1973\tHonor The Upstairs Room by Johanna Reiss\t380\t1973\tHonor Like Jake and Me by Mavis Jukes\t400\t1985\tHonor The Bears on Hemlock Mountain by Alice Dalgliesh\t490\t1953\tHonor Sweet Whispers, Brother Rush by Virginia Hamilton\t550\t1983\tHonor Sarah, Plain and Tall by Patricia MacLachlan\t560\t1986\tMedal Doctor DeSoto by William Steig\t560\t1983\tHonor Crazy Lady by Jane Leslie Conly\t570\t1994\tHonor The Whipping Boy by Sid Fleischman\t570\t1987\tMedal Carry On, Mr. Bowditch by Jean Lee Latham\t570\t1956\tMedal Al Capone Does My Shirts by Gennifer Choldenko\t600\t2005\tHonor After The Rain by Norma Fox Mazer\t600\t1988\tHonor A Year Down Yonder by by Richard Peck\t610\t2001\tMedal Because of Winn-Dixie by Kate DiCamillo\t610\t2001\tHonor Scorpions by Walter Dean Myers\t610\t1989\tHonor Courage of Sarah Noble by Alice Dalgliesh\t610\t1955\tHonor M. C. Higgins, the Great by Virginia Hamilton\t620\t1975\tMedal Somewhere in the Darkness by Walter Dean Myers\t640\t1993\tHonor In The Beginning: Creation Stories from Around the World by Virginia Hamilton\t640\t1989\tHonor The Good Master by Kate Seredy\t640\t1936\tHonor Pictures of Hollis Woods by Patricia Reilly Giff\t650\t2003\tHonor Strawberry Girl by Lois Lenski\t650\t1946\tMedal The Middle Moffat by Eleanor Estes\t650\t1943\tHonor The House of the Scorpion by Nancy Farmer\t660\t2003\tHonor Holes by Louis Sachar\t660\t1999\tMedal The Ear, the Eye and the Arm by Nancy Farmer\t660\t1995\tHonor The Voyages of Doctor Dolittle by Hugh Lofting\t660\t1923\tMedal The Tale of Despereaux by Kate DiCamillo, illustrated by Timothy Basil Ering\t670\t2004\tMedal Ella Enchanted by Gail Carson Levine\t670\t1998\tHonor Number the Stars by Lois Lowry\t670\t1990\tMedal Olive\u0026rsquo;s Ocean by Kevin Henkes\t680\t2004\tHonor Jennifer, Hecate, Macbeth, William McKinley, and Me, Elizabeth by E. L. Konigsburg\t680\t1968\tHonor The Family Under The Bridge by Natalie Savage Carlson\t680\t1959\tHonor Banner In The Sky by James Ullman\t680\t1955\tHonor Charlotte\u0026rsquo;s Web by E. B. White\t680\t1953\tHonor Wringer by Jerry Spinelli\t690\t1998\tHonor Hattie Big Sky by Kirby Larson\t700\t2007\tHonor The Hundred Penny Box by Sharon Bell Mathis\t700\t1976\tHonor Annie and the Old One by Miska Miles\t700\t1972\tHonor From the Mixed-Up Files of Mrs. Basil E. Frankweiler by E. L. Konigsburg\t700\t1968\tMedal Hope Was Here by Joan Bauer\t710\t2001\tHonor Yolonda\u0026rsquo;s Genius by Carol Fenner\t710\t1996\tHonor Dicey\u0026rsquo;s Song by Cynthia Voigt\t710\t1983\tMedal Onion John by Joseph Krumgold\t710\t1960\tMedal The Wheel on the School by Meindert DeJong\t710\t1955\tMedal Shadrach by Meindert Dejong\t710\t1954\tHonor Secret of the Andes by Ann Nolan Clark\t710\t1953\tMedal Rufus M. by Eleanor Estes\t710\t1944\tHonor Show Way by Jacqueline Woodson, illustrated by Hudson Talbott\t720\t2006\tHonor Lily\u0026rsquo;s Crossing by Patricia Reilly Giff\t720\t1998\tHonor The Wish Giver: Three Tales of Coven Tree by Bill Brittain\t720\t1984\tHonor Li Lun, Lad of Courage by Carolyn Treffinger\t720\t1948\tHonor The Cow-Tail Switch, and Other West African Stories by Harold Courlander\t720\t1948\tHonor On the Banks of Plum Creek by Laura Ingalls Wilder\t720\t1938\tHonor Penny from Heaven by Jennifer L. Holm\t730\t2007\tHonor A Girl Named Disaster by Nancy Farmer\t730\t1997\tHonor Dragon\u0026rsquo;s Gate by Laurence Yep\t730\t1994\tHonor The Dark-thirty: Southern Tales of the Supernatural by Patricia McKissack\t730\t1993\tHonor The Planet of Junior Brown by Virginia Hamilton\t730\t1972\tHonor Millions of Cats by Wanda Gág\t730\t1929\tHonor Kira-Kira by Cynthia Kadohata\t740\t2005\tMedal Getting Near to Baby by Audrey Couloumbis\t740\t2000\tHonor The True Confessions of Charlotte Doyle by Avi\t740\t1991\tHonor A Fine White Dust by Cynthia Rylant\t740\t1987\tHonor Shadow of a Bull by Maia Wojciechowska\t740\t1965\tMedal A Wrinkle in Time by Madeleine L\u0026rsquo;Engle\t740\t1963\tMedal When You Reach Me by Rebecca Stead\t750\t2010\tMedal After Tupac \u0026amp; D Foster by Jacqueline Woodson\t750\t2009\tHonor A Corner of The Universe by Ann M. Martin\t750\t2003\tHonor A Long Way from Chicago by Richard Peck\t750\t1999\tHonor On My Honor by Marion Dane Bauer\t750\t1987\tHonor The Westing Game by Ellen Raskin\t750\t1979\tMedal The Perilous Road by William O. Steele\t750\t1959\tHonor Miracles on Maple Hill by Virginia Sorensen\t750\t1957\tMedal The Corn Grows Ripe by Dorothy Rhoads\t750\t1957\tHonor Hurry Home, Candy by Meindert Dejong\t750\t1954\tHonor The Apple and the Arrow by Mary \u0026amp; Conrad Buff\t750\t1952\tHonor Misty of Chincoteague by Marguerite Henry\t750\t1948\tHonor Feathers by Jacqueline Woodson\t760\t2008\tHonor Whittington by Alan Armstrong, illustrated by S.D. Schindler\t760\t2006\tHonor Hoot by Carl Hiaasen\t760\t2003\tHonor 26 Fairmount Avenue by Tomie dePaola\t760\t2000\tHonor Belle Prater\u0026rsquo;s Boy by Ruth White\t760\t1997\tHonor The Giver by Lois Lowry\t760\t1994\tMedal Knee Knock Rise by Natalie Babbitt\t760\t1971\tHonor The Black Cauldron by Lloyd Alexander\t760\t1966\tHonor The Bronze Bow by Elizabeth George Speare\t760\t1962\tMedal Gone-Away Lake by Elizabeth Enright\t760\t1958\tHonor Walk Two Moons by Sharon Creech\t770\t1995\tMedal The Sign of the Beaver by Elizabeth George Speare\t770\t1984\tHonor A Solitary Blue by Cynthia Voigt\t770\t1984\tHonor My Brother Sam is Dead by James Lincoln Collier \u0026amp; Christopher Collier\t770\t1975\tHonor Kildee House by Rutherford Montgomery\t770\t1950\tHonor The Singing Tree by Kate Seredy\t770\t1940\tHonor Rules by Cynthia Lord\t780\t2007\tHonor Crispin: The Cross of Lead by Avi\t780\t2003\tMedal Figgs \u0026amp; Phantoms by Ellen Raskin\t780\t1975\tHonor The Cricket In Times Square by George Selden\t780\t1961\tHonor Chucaro: Wild Pony of the Pampa by Francis Kalnay\t780\t1959\tHonor And Now Miguel by Joseph Krumgold\t780\t1954\tMedal The Silver Pencil by Alice Dalgliesh\t780\t1945\tHonor Shen of the Sea by Arthur Bowie Chrisman\t780\t1926\tMedal Mrs. Frisby and the Rats of NIMH by Robert C. O\u0026rsquo;Brien\t790\t1972\tMedal The Noonday Friends by Mary Stolz\t790\t1966\tHonor The Long Winter by Laura Ingalls Wilder\t790\t1941\tHonor Joey Pigza Loses Control by Jack Gantos\t800\t2001\tHonor The Fledgling by Jane Langton\t800\t1981\tHonor The Great Gilly Hopkins by Katherine Paterson\t800\t1979\tHonor Fog Magic by Julia Sauer\t800\t1944\tHonor Indian Captive: The Story of Mary Jemison by Lois Lenski\t800\t1942\tHonor A Ring of Endless Light by Madeleine L\u0026rsquo;Engle\t810\t1981\tHonor Bridge to Terabithia by Katherine Paterson\t810\t1978\tMedal A String in the Harp by Nancy Bond\t810\t1977\tHonor It\u0026rsquo;s Like This, Cat by Emily Neville\t810\t1964\tMedal The Loner by Ester Wier\t810\t1964\tHonor My Side of the Mountain by Jean Craighead George\t810\t1960\tHonor Seabird by Holling C. Holling\t810\t1949\tHonor Thimble Summer by Elizabeth Enright\t810\t1939\tMedal Roller Skates by Ruth Sawyer\t810\t1937\tMedal Where the Mountain Meets the Moon by Grace Lin\t820\t2010\tHonor The Graveyard Book by Neil Gaiman, illus. by Dave McKean\t820\t2009\tMedal Criss Cross by Lynne Rae Perkins\t820\t2006\tMedal Surviving the Applewhites by Stephanie S. Tolan\t820\t2003\tHonor Maniac Magee by Jerry Spinelli\t820\t1991\tMedal Afternoon of the Elves by Janet Taylor Lisle\t820\t1990\tHonor Sing Down the Moon by Scott O\u0026rsquo;Dell\t820\t1971\tHonor The House of Sixty Fathers by Meindert DeJong\t820\t1957\tHonor The Light at Tern Rock by Julia Sauer\t820\t1952\tHonor The Avion My Uncle Flew by Cyrus Fisher\t820\t1947\tHonor By the Shores of Silver Lake by Laura Ingalls Wilder\t820\t1940\tHonor The Evolution of Calpurnia Tate by Jacqueline Kelly\t830\t2010\tHonor The Underneath by Kathi Appelt, illus. by David Small\t830\t2009\tHonor The Wanderer by Sharon Creech\t830\t2001\tHonor Volcano: The Eruption and Healing of Mount St. Helens by Patricia Lauber\t830\t1987\tHonor Upon the Head of the Goat: A Childhood in Hungary 1939-1944 by Aranka Siegal\t830\t1982\tHonor Summer of the Swans by Betsy Byars\t830\t1971\tMedal King of the Wind by Marguerite Henry\t830\t1949\tMedal Call It Courage by Armstrong Sperry\t830\t1941\tMedal Ramona and Her Father by Beverly Cleary\t840\t1978\tHonor The Tombs of Atuan by Ursula K. LeGuin\t840\t1972\tHonor The King\u0026rsquo;s Fifth by Scott O\u0026rsquo;Dell\t840\t1967\tHonor Johnny Tremain by Esther Forbes\t840\t1944\tMedal These Happy Golden Years by Laura Ingalls Wilder\t840\t1944\tHonor When Shlemiel Went to Warsaw and Other Stories by Isaac Bashevis Singer\t850\t1969\tHonor Zlateh The Goat and Other Stories by Isaac Bashevis Singer\t850\t1967\tHonor The Witch of Blackbird Pond by Elizabeth George Speare\t850\t1959\tMedal Little Town on the Prairie by Laura Ingalls Wilder\t850\t1942\tHonor Homesick: My Own Story by Jean Fritz\t860\t1983\tHonor Ramona Quimby, Age 8 by Beverly Cleary\t860\t1982\tHonor Julie of the Wolves by Jean Craighead George\t860\t1973\tMedal The Matchlock Gun by Walter Edmonds\t860\t1942\tMedal The View from Saturday by E.L. Konigsburg\t870\t1997\tMedal Graven Images by Paul Fleischman\t870\t1983\tHonor Dragonwings by Laurence Yep\t870\t1976\tHonor Miss Hickory by Carolyn Sherwin Bailey\t870\t1947\tMedal The Hundred Dresses by Eleanor Estes\t870\t1945\tHonor Jacob Have I Loved by Katherine Paterson\t880\t1981\tMedal Anpao: An American Indian Odyssey by Jamake Highwater\t880\t1978\tHonor Old Ramon by Jack Schaefer\t880\t1961\tHonor Justin Morgan Had a Horse by Marguerite Henry\t880\t1946\tHonor Princess Academy by Shannon Hale\t890\t2006\tHonor Carver: A Life In Poems by Marilyn Nelson\t890\t2002\tHonor Shiloh by Phyllis Reynolds Naylor\t890\t1992\tMedal Caddie Woodlawn by Carol Ryrie Brink\t890\t1936\tMedal Young Fu of the Upper Yangtze by Elizabeth Lewis\t890\t1933\tMedal Our Only May Amelia by Jennifer L. Holm\t900\t2000\tHonor What Hearts by Bruce Brooks\t900\t1993\tHonor Philip Hall Likes Me, I Reckon Maybe by Bette Greene\t900\t1975\tHonor The Headless Cupid by Zilpha Keatley Snyder\t900\t1972\tHonor Sounder by William H. Armstrong\t900\t1970\tMedal The High King by Lloyd Alexander\t900\t1969\tMedal Abraham Lincoln, Friend of the People by Clara Ingram Judson\t900\t1951\tHonor Dear Mr. Henshaw by Beverly Cleary\t910\t1984\tMedal Enchantress From the Stars by Sylvia Louise Engdahl\t910\t1971\tHonor Rifles for Watie by Harold Keith\t910\t1958\tMedal Old Yeller by Fred Gipson\t910\t1957\tHonor Minn of the Mississippi by Holling C. Holling\t910\t1952\tHonor Mr. Popper\u0026rsquo;s Penguins by Richard \u0026amp; Florence Atwater\t910\t1939\tHonor Day On Skates: The Story of a Dutch Picnic by Hilda Von Stockum\t910\t1935\tHonor A Single Shard by Linda Sue Park\t920\t2002\tMedal The Thief by Megan Whalen Turner\t920\t1997\tHonor Roll of Thunder, Hear My Cry by Mildred D. Taylor\t920\t1977\tMedal Abel\u0026rsquo;s Island by William Steig\t920\t1977\tHonor The Dark Is Rising by Susan Cooper\t920\t1974\tHonor The Witches of Worm by Zilpha Keatley Snyder\t920\t1973\tHonor The Animal Family by Randall Jarrell\t920\t1966\tHonor Blue Willow by Doris Gates\t920\t1941\tHonor Dogsong by Gary Paulsen\t930\t1986\tHonor The Grey King by Susan Cooper\t930\t1976\tMedal Journey Outside by Mary Q. Steele\t930\t1970\tHonor The Jazz Man by Mary Hays Weik\t930\t1967\tHonor The Golden Goblet by Eloise Jarvis McGraw\t930\t1962\tHonor Moorchild by Eloise McGraw\t940\t1997\tHonor The Mostly True Adventures of Homer P. Figg by Rodman Philbrick\t950\t2010\tHonor Everything on a Waffle by Polly Horvath\t950\t2002\tHonor Bud, Not Buddy by Christopher Paul Curtis\t950\t2000\tMedal The Gammage Cup by Carol Kendall\t950\t1960\tHonor Along Came A Dog by Meindert Dejong\t950\t1959\tHonor A Gathering of Days: A New England Girl\u0026rsquo;s Journal, 1830-1832 by Joan W. Blos\t960\t1980\tMedal Moccasin Trail by Eloise Jarvis McGraw\t960\t1953\tHonor Shabanu, Daughter of the Wind by Suzanne Fisher Staples\t970\t1990\tHonor The Slave Dancer by Paula Fox\t970\t1974\tMedal Missing May by Cynthia Rylant\t980\t1993\tMedal Sugaring Time by Kathryn Lasky\t980\t1984\tHonor The Black Pearl by Scott O\u0026rsquo;Dell\t980\t1968\tHonor The Golden Fleece and The Heroes Who Lived Before Achilles by Padraic Colum\t980\t1922\tHonor The Wednesday Wars by Gary D. Schmidt\t990\t2008\tHonor The Road from Home: The Story of an Armenian Girl by David Kherdian\t990\t1980\tHonor The Great Wheel by Robert Lawson\t990\t1958\tHonor Ginger Pye by Eleanor Estes\t990\t1952\tMedal My Father\u0026rsquo;s Dragon by Ruth S. Gannett\t990\t1949\tHonor Claudette Colvin: Twice Toward Justice by Phillip Hoose\t1000\t2010\tHonor Lizzie Bright and the Buckminster Boy by Gary D. Schmidt\t1000\t2005\tHonor The Watsons Go to Birmingham: 1963 by Christopher Paul Curtis\t1000\t1996\tHonor One-Eyed Cat by Paula Fox\t1000\t1985\tHonor Island of the Blue Dolphins by Scott O\u0026rsquo;Dell\t1000\t1961\tMedal Daughter of the Mountains by Louise Rankin\t1000\t1949\tHonor The Cat Who Went to Heaven by Elizabeth Coatsworth\t1000\t1931\tMedal The Higher Power of Lucky by Susan Patron, illus. by Matt Phelan\t1010\t2007\tMedal What Jamie Saw by Carolyn Coman\t1010\t1996\tHonor The Egypt Game by Zilpha Keatley Snyder\t1010\t1968\tHonor Hatchet by Gary Paulsen\t1020\t1988\tHonor The Perilous Gard by Elizabeth Marie Pope\t1020\t1975\tHonor The White Stag by Kate Seredy\t1020\t1938\tMedal The Blue Sword by Robin McKinley\t1030\t1983\tHonor Tree of Freedom by Rebecca Caudill\t1030\t1950\tHonor Adam of the Road by Elizabeth Janet Gray\t1030\t1943\tMedal Gay Neck, the Story of a Pigeon by Dhan Gopal Mukerji\t1040\t1928\tMedal Hitler Youth: Growing Up in Hitler\u0026rsquo;s Shadow by Susan Campbell Bartoletti\t1050\t2006\tHonor Rabbit Hill by Robert Lawson\t1050\t1945\tMedal Calico Bush by Rachel Field\t1060\t1932\tHonor Savvy by Ingrid Law\t1070\t2009\tHonor Elijah of Buxton by Christopher Paul Curtis\t1070\t2008\tHonor Commodore Perry In the Land of the Shogun by Rhoda Blumberg\t1070\t1986\tHonor The Twenty-One Balloons by William Pène du Bois\t1070\t1948\tMedal To Be a Slave by Julius Lester\t1080\t1969\tHonor Davy Crockett by Constance Rourke\t1080\t1935\tHonor Amos Fortune, Free Man by Elizabeth Yates\t1090\t1951\tMedal Eleanor Roosevelt: A Life of Discovery by Russell Freedman\t1100\t1994\tHonor I, Juan de Pareja by Elizabeth Borton de Trevino\t1100\t1966\tMedal Across Five Aprils by Irene Hunt\t1100\t1965\tHonor Lincoln: A Photobiography by Russell Freedman\t1110\t1988\tMedal The Door in the Wall by Marguerite de Angeli\t1110\t1950\tMedal The Hero and the Crown by Robin McKinley\t1120\t1985\tMedal An American Plague by Jim Murphy\t1130\t2004\tHonor The Great Fire by Jim Murphy\t1130\t1996\tHonor Up a Road Slowly by Irene Hunt\t1130\t1967\tMedal Rascal: A Memoir of a Better Era by Sterling North\t1140\t1964\tHonor The Moves Make the Man by Bruce Brooks\t1150\t1985\tHonor Invincible Louisa: The Story of the Author of Little Women by Cornelia Meigs\t1150\t1934\tMedal The Wright Brothers: How They Invented the Airplane by Russell Freedman\t1160\t1992\tHonor Swift Rivers by Cornelia Meigs\t1160\t1933\tHonor Catherine, Called Birdy by Karen Cushman\t1170\t1995\tHonor The Winter Room by Gary Paulsen\t1170\t1990\tHonor The Voice that Challenged a Nation by Russell Freedman\t1180\t2005\tHonor Hitty, Her First Hundred Years by Rachel Field\t1180\t1930\tMedal Incident At Hawk\u0026rsquo;s Hill by Allan W. Eckert\t1200\t1972\tHonor The Trumpeter of Krakow by Eric P. Kelly\t1200\t1929\tMedal The Dark Frigate by Charles Hawes\t1230\t1924\tMedal The Midwife\u0026rsquo;s Apprentice by Karen Cushman\t1240\t1996\tMedal The Story of Mankind by Hendrik Willem van Loon\t1260\t1922\tMedal The Horsecatcher by Mari Sandoz\t1310\t1958\tHonor Tales from Silver Lands by Charles Finger\t1320\t1925\tMedal Our Eddie by Sulamith Ish-Kishor\t?\t1970\tHonor The Many Ways of Seeing: An Introduction to the Pleasures of Art by Janet Gaylord Moore\t?\t1970\tHonor The Fearsome Inn by Isaac Bashevis Singer\t?\t1968\tHonor Thistle and Thyme: Tales and Legends from Scotland by Sorche Nic Leodhas\t?\t1963\tHonor Men of Athens by Olivia Coolidge\t?\t1963\tHonor Frontier Living by Edwin Tunis\t?\t1962\tHonor Belling The Tiger by Mary Stolz\t?\t1962\tHonor America Moves Forward: A History for Peter by Gerald W. Johnson\t?\t1961\tHonor America Is Born: A History for Peter by Gerald W. Johnson\t?\t1960\tHonor Tom Paine, Freedom\u0026rsquo;s Apostle by Leo Gurko\t?\t1958\tHonor Mr. Justice Holmes by Clara Ingram Judson\t?\t1957\tHonor Black Fox of Lorne by Marguerite de Angeli\t?\t1957\tHonor The Secret River by Marjorie Kinnan Rawlings\t?\t1956\tHonor The Golden Name Day by Jennie Lindquist\t?\t1956\tHonor Men, Microscopes, and Living Things by Katherine Shippen\t?\t1956\tHonor All Alone by Claire Huchet Bishop\t?\t1954\tHonor Theodore Roosevelt, Fighting Patriot by Clara Ingram Judson\t?\t1954\tHonor Magic Maize by Mary \u0026amp; Conrad Buff\t?\t1954\tHonor Red Sails to Capri by Ann Weil\t?\t1953\tHonor Birthdays of Freedom, Vol. 1 by Genevieve Foster\t?\t1953\tHonor Americans Before Columbus by Elizabeth Baity\t?\t1952\tHonor The Defender by Nicholas Kalashnikoff\t?\t1952\tHonor Better Known as Johnny Appleseed by Mabel Leigh Hunt\t?\t1951\tHonor Gandhi, Fighter Without a Sword by Jeanette Eaton\t?\t1951\tHonor The Story of Appleby Capple by Anne Parrish\t?\t1951\tHonor The Blue Cat of Castle Town by Catherine Coblentz\t?\t1950\tHonor George Washington by Genevieve Foster\t?\t1950\tHonor Song of The Pines by Walter \u0026amp; Marion Havighurst\t?\t1950\tHonor Story of the Negro by Arna Bontemps\t?\t1949\tHonor Pancakes-Paris by Claire Huchet Bishop\t?\t1948\tHonor The Quaint and Curious Quest of Johnny Longfoot by Catherine Besterman\t?\t1948\tHonor Wonderful Year by Nancy Barnes\t?\t1947\tHonor Big Tree by Mary \u0026amp; Conrad Buff\t?\t1947\tHonor The Heavenly Tenants by William Maxwell\t?\t1947\tHonor The Hidden Treasure of Glaston by Eleanor Jewett\t?\t1947\tHonor The Moved-Outers by Florence Crannell Means\t?\t1946\tHonor Bhimsa, the Dancing Bear by Christine Weston\t?\t1946\tHonor New Found World by Katherine Shippen\t?\t1946\tHonor Abraham Lincoln\u0026rsquo;s World by Genevieve Foster\t?\t1945\tHonor Lone Journey: The Life of Roger Williams by Jeanetter Eaton\t?\t1945\tHonor Mountain Born by Elizabeth Yates\t?\t1944\tHonor Have You Seen Tom Thumb? by Mabel Leigh Hunt\t?\t1943\tHonor George Washington\u0026rsquo;s World by Genevieve Foster\t?\t1942\tHonor Down Ryton Water by Eva Roe Gaggin\t?\t1942\tHonor Young Mac of Fort Vancouver by Mary Jane Carr\t?\t1941\tHonor Nansen by Anna Gertrude Hall\t?\t1941\tHonor Daniel Boone by James Daugherty\t?\t1940\tMedal Runner of the Mountain Tops: The Life of Louis Agassiz by Mabel Robinson\t?\t1940\tHonor Boy with a Pack by Stephen W. Meader\t?\t1940\tHonor Nino by Valenti Angelo\t?\t1939\tHonor Hello the Boat! by Phyllis Crawford\t?\t1939\tHonor Leader By Destiny: George Washington, Man and Patriot by Jeanette Eaton\t?\t1939\tHonor Penn by Elizabeth Janet Gray\t?\t1939\tHonor Pecos Bill by James Cloyd Bowman\t?\t1938\tHonor Bright Island by Mabel Robinson\t?\t1938\tHonor Phebe Fairchild: Her Book by Lois Lenski\t?\t1937\tHonor Whistler\u0026rsquo;s Van by Idwal Jones\t?\t1937\tHonor The Golden Basket by Ludwig Bemelmans\t?\t1937\tHonor Winterbound by Margery Bianco\t?\t1937\tHonor The Codfish Musket by Agnes Hewes\t?\t1937\tHonor Audubon by Constance Rourke\t?\t1937\tHonor Honk, the Moose by Phil Stong\t?\t1936\tHonor Young Walter Scott by Elizabeth Janet Gray\t?\t1936\tHonor All Sail Set: A Romance of the Flying Cloud by Armstrong Sperry\t?\t1936\tHonor Dobry by Monica Shannon\t?\t1935\tMedal Pageant of Chinese History by Elizabeth Seeger\t?\t1935\tHonor The Forgotten Daughter by Caroline Snedeker\t?\t1934\tHonor Swords of Steel by Elsie Singmaster\t?\t1934\tHonor Winged Girl of Knossos by Erik Berry\t?\t1934\tHonor New Land by Sarah Schmidt\t?\t1934\tHonor Big Tree of Bunlahy: Stories of My Own Countryside by Padraic Colum\t?\t1934\tHonor Glory of the Seas by Agnes Hewes\t?\t1934\tHonor Apprentice of Florence by Ann Kyle\t?\t1934\tHonor The Railroad To Freedom: A Story of the Civil War by Hildegarde Swift\t?\t1933\tHonor Children of the Soil: A Story of Scandinavia by Nora Burglon\t?\t1933\tHonor Waterless Mountain by Laura Adams Armer\t?\t1932\tMedal The Fairy Circus by Dorothy P. Lathrop\t?\t1932\tHonor Boy of the South Seas by Eunice Tietjens\t?\t1932\tHonor Out of the Flame by Eloise Lownsbery\t?\t1932\tHonor Jane\u0026rsquo;s Island by Marjorie Allee\t?\t1932\tHonor Truce of the Wolf and Other Tales of Old Italy by Mary Gould Davis\t?\t1932\tHonor Floating Island by Anne Parrish\t?\t1931\tHonor The Dark Star of Itza: The Story of A Pagan Princess by Alida Malkus\t?\t1931\tHonor Queer Person by Ralph Hubbard\t?\t1931\tHonor Mountains are Free by Julie Davis Adams\t?\t1931\tHonor Spice and the Devil\u0026rsquo;s Cave by Agnes Hewes\t?\t1931\tHonor Meggy MacIntosh by Elizabeth Janet Gray\t?\t1931\tHonor Garram the Hunter: A Boy of the Hill Tribes by Herbert Best\t?\t1931\tHonor Ood-Le-Uk the Wanderer by Alice Lide \u0026amp; Margaret Johansen\t?\t1931\tHonor A Daughter of the Seine: The Life of Madame Roland by Jeanette Eaton\t?\t1930\tHonor Pran of Albania by Elizabeth Miller\t?\t1930\tHonor Jumping-Off Place by Marion Hurd McNeely\t?\t1930\tHonor The Tangle-Coated Horse and Other Tales by Ella Young\t?\t1930\tHonor Vaino by Julia Davis Adams\t?\t1930\tHonor Little Blacknose by Hildegarde Swift\t?\t1930\tHonor Pigtail of Ah Lee Ben Loo by John Bennett\t?\t1929\tHonor The Boy Who Was by Grace Hallock\t?\t1929\tHonor Clearing Weather by Cornelia Meigs\t?\t1929\tHonor Runaway Papoose by Grace Moon\t?\t1929\tHonor Tod of the Fens by Elinor Whitney\t?\t1929\tHonor The Wonder Smith and His Son by Ella Young\t?\t1928\tHonor Downright Dencey by Caroline Snedeker\t?\t1928\tHonor Smoky, the Cowhorse by Will James\t?\t1927\tMedal The Voyagers: Being Legends and Romances of Atlantic Discovery by Padraic Colum\t?\t1926\tHonor Nicholas: A Manhattan Christmas Story\t?\t1925\tHonor The Dream Coach by Anne Parrish\t?\t1925\tHonor The Great Quest by Charles Hawes\t?\t1922\tHonor Cedric the Forester by Bernard Marshall\t?\t1922\tHonor The Old Tobacco Shop by William Bowen\t?\t1922\tHonor The Windy Hill by Cornelia Meigs\t?\t1922\tHonor The Surrender Tree: Poems of Cuba\u0026rsquo;s Struggle for Freedom by Margarita Engle\tNP\t2009\tHonor Good Masters! Sweet Ladies! Voices from a Medieval Village by Laura Amy Schlitz\tNP\t2008\tMedal Out of the Dust by Karen Hesse\tNP\t1998\tMedal Nothing But The Truth: a Documentary Novel by Avi\tNP\t1992\tHonor Joyful Noise: Poems for Two Voices by Paul Fleischman\tNP\t1989\tMedal A Visit to William Blake\u0026rsquo;s Inn by Nancy Willard\tNP\t1982\tMedal\nDownloading books from following url http://playpen.meraka.csir.co.za/~acdc/education/Dr_Anvind_Gupa/Learners_Library_7_March_2007/Resources/books/\nhttp://www.arvindguptatoys.com/\n720L Twilight\nNewbery\n520L 2013 Flora and Ulysses 570L 1987 The Whipping Boy no audio 610L 2001 A Year Down Yonder no audio 660L 1999 Holes no audio 750L 2010 When You Reach Me 750L 2011 One Crazy Summer no pdf 760L 1994 The Giver 800L 2011 Moon Over Manifest 820L 2010 Where the Mountain Meets the Moon no pdf 830L 2010 The Evolution of Calpurnia Tate no pdf 830L 2009 The Underneath no pdf 880L 1981 Jacob Have I loved no audio 950L 2010 The Mostly True Adventures of Homer P. Figg no pdf\nThe Secret Garden 970L A Christmas Carol 900L Alice’s Adventures in Wonderland 980L Uncle Tom’s Cabin 1050L Around the World in 80 Days 1070L The Jungle Book NC1100L The Jungle 1170 Heidi 1200L Little Women 1300L Scarlet Letter 1340L\n"},{"id":13,"href":"/","title":"","parent":"","content":"我的笔记    "},{"id":14,"href":"/01-%E7%BC%96%E7%A8%8B%E8%AF%AD%E8%A8%80/","title":"01 编程语言","parent":"","content":""},{"id":15,"href":"/02-%E5%BC%80%E5%8F%91%E5%B7%A5%E5%85%B7/","title":"02 开发工具","parent":"","content":""},{"id":16,"href":"/06-%E6%93%8D%E4%BD%9C%E7%B3%BB%E7%BB%9F/","title":"06 操作系统","parent":"","content":""},{"id":17,"href":"/07-%E5%B5%8C%E5%85%A5%E5%BC%8F/","title":"07 嵌入式","parent":"","content":""},{"id":18,"href":"/08-%E8%99%9A%E6%8B%9F%E5%8C%96/","title":"08 虚拟化","parent":"","content":""},{"id":19,"href":"/09-%E6%95%B0%E6%8D%AE%E5%AD%98%E5%82%A8/","title":"09 数据存储","parent":"","content":""},{"id":20,"href":"/10-%E5%BC%80%E5%8F%91%E8%B5%84%E6%96%99/","title":"10 开发资料","parent":"","content":""},{"id":21,"href":"/20-%E8%8B%B1%E8%AF%AD%E5%AD%A6%E4%B9%A0/","title":"20 英语学习","parent":"","content":""},{"id":22,"href":"/categories/","title":"Categories","parent":"","content":""},{"id":23,"href":"/02-%E5%BC%80%E5%8F%91%E5%B7%A5%E5%85%B7/GCC/","title":"GCC","parent":"02 开发工具","content":"GCC    编译选项     -c 预处理、编译和汇编源文件，但不链接 -S 编译后即停止，不汇编 -E 预处理后即停止 -Wall 显示所有警告 -g 加入调试信息 -O 优化选项，有多个-O时最后一个生效  连接器选项      -lmylib 寻找libmylib.a库文件\n  -nostartfiles 不链接系统启动文件，在编译bootloader、kernel时有用\n  -nostdlib 不链接系统启动文件和标准库文件\n  -static 生成静态文件，不使用共享库\n  -shared 生成共享库文件\n  -T 指定代码段、数据段、bss段的起始地址，也可以用来指定一个链接脚本\n   如何查看编译器预定义的符号 touch a.h gcc -E -dM a.h\n  编译错误    "},{"id":24,"href":"/02-%E5%BC%80%E5%8F%91%E5%B7%A5%E5%85%B7/GDB/","title":"GDB","parent":"02 开发工具","content":"GDB Commands     list 查看源代码 回车表示命令重复 break 断点  break line number break function name info break   r 运行程序 n 单步运行next step over s 单步运行step in c 继续运行continue p 打印变量print bt 查看函数堆栈 finish 退出函数 info registers 查看寄存器 commands break_list 每次进入断点后执行的命令   "},{"id":25,"href":"/02-%E5%BC%80%E5%8F%91%E5%B7%A5%E5%85%B7/iOS/","title":"iOS","parent":"02 开发工具","content":"iOS      命令行编译打包iOS App xcodebuild -sdk iphoneos9.1 -target AHD_iPhone_3.5 -configuration Release CODE_SIGN_IDENTITY=\u0026ldquo;iPhone Developer: bingxue zhang (CAP3RNPRFC)\u0026rdquo; clean build\nxcrun -sdk iphoneos PackageApplication -v build/Release-iphoneos/AHD_iPhone_3.5.app -o build/Release-iphoneos/AHD_iPhone_3.5.ipa \u0026ndash;sign \u0026ldquo;iPhone Developer: bingxue zhang (CAP3RNPRFC)\u0026rdquo;\n/usr/bin/xcrun -sdk iphoneos PackageApplication -v \u0026ldquo;${RELEASE_BUILDDIR}/${APPLICATION_NAME}.app\u0026rdquo; -o \u0026ldquo;${BUILD_HISTORY_DIR}/${APPLICATION_NAME}.ipa\u0026rdquo; \u0026ndash;sign \u0026ldquo;${DEVELOPER_NAME}\u0026rdquo; \u0026ndash;embed \u0026ldquo;${PROVISONING_PROFILE}”\n   "},{"id":26,"href":"/07-%E5%B5%8C%E5%85%A5%E5%BC%8F/JLink/","title":"JLink","parent":"07 嵌入式","content":"JLink    "},{"id":27,"href":"/06-%E6%93%8D%E4%BD%9C%E7%B3%BB%E7%BB%9F/MacOSX/","title":"MacOSX","parent":"06 操作系统","content":"mysqld    /usr/local/mysql/support-files/mysql.server  Installing the Cross compile tools    brew install musl-cross \u0026ndash;with-arm \u0026ndash;with-mips\nchrome 跨域    \u0026ndash;disable-web-security \u0026ndash;user-data-dir\n#mysql 查看和打开日志 SHOW VARIABLES LIKE \u0026ldquo;general_log%\u0026quot;;\nSET GLOBAL general_log = \u0026lsquo;ON\u0026rsquo;;\n"},{"id":28,"href":"/09-%E6%95%B0%E6%8D%AE%E5%AD%98%E5%82%A8/MySQL/","title":"MySQL","parent":"09 数据存储","content":"语法    "},{"id":29,"href":"/07-%E5%B5%8C%E5%85%A5%E5%BC%8F/QQ2440/","title":"QQ2440","parent":"07 嵌入式","content":"QQ2440    硬件信息    触摸屏：ltv350qv-f04-0br 320*240 24bit\n地址空间映射    0x00000000 - 0x00001000 Nand Flash的前4k 0x30000000 - 0x33FFFFFF 64M SDRAM 0x30000000 - 0x3FFFFFFF 128M*2 SDRAM 地址空间 0x48000000 - 0x5FFFFFFF 寄存器地址空间 0x48000000 - 0x48000030 存储控制器  寄存器    PC的值为当前正在执行的指令+8 CPSR\n 31 30 29 28 7 6 5 4 3 2 1 0 | N | Z | C | V | | I | F | T | M4 | M3 | M2 | M1 | M0 | T[5] 为1表示CPU处于THUMB状态，为0表示处于ARM状态。 I位和F位为1表示禁止IRQ和FIQ. M[4:0] 10000 User 用户模式 10001 FIQ 快速中断模式 10010 IRQ 中断模式 10011 SVC 管理模式 10111 ABORT 数据访问中止模式 11011 UNDEFINED 未定义指令中止模式 11111 SYSTEM 系统模式  GPIO 0x56000000    GPxCON寄存器\nPORTA 每位对应一个引脚 PORT B ~ PORTH/J中每两位控制一根引脚，00表示输入、01表示输出、10表示特殊功能、11保留  GPxDAT GPxUP\n存储控制器 0x48000000    一共有13个存储控制器。\n 位宽和等待控制寄存器 BWSCON(BUS WIDTH \u0026amp; WAIT CONTROL REGISTER) 每4位控制一个BANK。 STx：启动/禁止SDRAM的数据掩码引脚，对于SDRAM，此位为0；对于SRAM，此位为1。 WSx：是否使用存储器的WAIT信号，通常设为0。 DWx：使用两位来设置BANK的位宽，00为8位；01为16位；10为32为；11保留。 比较特殊的是BANK0，它没有ST0和WS0，DW0为只读，由硬件跳线觉得，只有16、32两种位宽。 例如：BWSCON的值为0x22011110。 BANK控制寄存器 BANKCONx(BANK CONTROL REGISTER，x为0-5) 外接设备的访问时序，使用默认的0x0700即可。 BANK控制寄存器 BANKCONx(BANK CONTROL REGISTER，x为6-7) 在8个BANK中，只有BANK6和BANK7可以外接SRAM或SDRAM。 MT([16:15])：用于设置本BANK外接的是ROM/SRAM还是SDRAM。00为SRAM，11为SDRAM。 当MT=00时，此寄存器与BANKCON0 ~ BANKCON5类似；当MT=11时，此寄存器其他值如下： Trcd([3:2])：RAS to CAS delay，设为推荐值01。 SCAN([1:0])：SDRAM的列地址位数。00表示8位，01表示9位，10表示10位。 例如：BANKCON6/7可设为0x00018005。 刷新控制寄存器REFRESH(REFRESH CONTROL REGISTER)：设为0x008C0000 + R_CNT REFEN([23])：0为禁止SDRAM的刷新功能，1为开启SDRAM的刷新功能。 TREFMD([22])：SDRAM的刷新模式，0为CBR/Auto Refresh，1为Self Refresh（一般在系统休眠时使用）。 Trp([21:20])：设为0即可。 Tsrc([19:18])：设为11即可。 Refresh Counter([10:0])：即上述的R_CNT。 R_CNT = 2^11 + 1 - SDRAM时钟频率(MHz) * SDRAM刷新周期(uS) 例如：未使用PLL时，R_CNT = 2^11 + 1 - 12 * 64/8192 = 1955 = 0x07A3 BANKSIZE寄存器（BANKSIZE REGISTER） BURST_EN([7])：0为ARM核禁止突发传输，1为ARM核支持突发传输。 SCKE_EN([5])：0为不使用SCKE信号令SDRAM进入省电模式，1为使用SCKE信号。 SCLK_EN([4])：0为时刻发出SCLK信号，1为仅在访问SDRAM时才发出SCLK信号（推荐）。 BK76MAP([2:0])：设置BANK6/7的大小。 010 = 128M/128M， 001 = 64M/64M， 000 = 32M/32M 111 = 16M/16M，110 = 8M/8M，101 = 4M/4M， 100 = 2M/2M 例如：BANK6外接64M的SDRAM，BANKSIZE可设置为0XB1。 SDRAM模式设置寄存器MRSRBx(SDRAM MODE REGISTER SET REGISTER，x为6~7) CL([6:4])：SDRAM时序的时间参数。 000 = 1 clock， 010 = 2 clocks， 011 = 3 clocks 例如：MRSRB6/7可设置为0x30。  MMU    NAND Flash控制器(2440) 0x4E000000     NFCONF NAND Flash控制寄存器 设置NAND Flash的时序参数TACLS、TWRPH0、TWRPH1，设置数据位宽。 NFCONT：S3C2410没有这个寄存器 使能或禁止NAND Flash控制器，使能或禁止控制引脚信号nFCE、初始化ECC。 NFCMD ：NAND Flash命令寄存器 NFADDR ：NAND Flash地址寄存器 NFDATA ：NAND Flash数据寄存器 NFSTAT ：NAND Flash状态寄存器 只用到位0，0：busy，1：ready。  中断    中断模式异常向量地址：0x00000018 快速中断异常向量地址：0x0000001C\n中断寄存器\n SUBSRCPND (SUB SOURCE PENDING) SUBSRCPND寄存器用来标识INT_RXD0、INT_TXD0等中断（S3C2440有15个这类中断，2410有11个）。 某位为1表示发生中断。 清除中断时，往SUBSRCPND某位写1即可令此位为0，写入0无效果。 INTSUBMSK (INTERRUPT SUB MASK) 某位为1表示对应的中断被屏蔽 SRCPND(SOURCE PENDING) INTMSK(INTERRUPT MASK) 只能屏蔽IRQ中断，不能屏蔽FIQ中断 INTMOD(INTERRUPT MODE) 某位为1表示FIQ，只能有一位被设为1 PRIORITY 中断优先级的判断通过7个仲裁器来完成，包括6各一级仲裁器和1个二级仲裁器。 PRIORITY寄存器使用3位来控制每个仲裁器，ARB_MODE([0:6])和ARB_SEL(7:20) INTPND(INTERRUPT PENDING) 经过中断优先级仲裁后，优先级最高的中断在INTPND寄存器被置位，同一时间只能有一位被置1。 清楚中断时，往这个位写1。 INTOFFSET(INTERRUPT OFFSET) 表示INTPND寄存器中哪位被置1了。 在清除SRCPND、INTPND寄存器时，INTOFFSET寄存器被自动清楚。  系统时钟和定时器    PLL时钟控制逻辑给整个芯片提供三种时钟：FCLK用于CPU核；HCLK用于AHB；PCLK用于APB。 AHB(Advanced High Performance Bus)主要用于高性能模块，如CPU、DMA和DSP等。 APB(Advanced Peripheral Bus)用于低带宽的周边外设，如UART、I2C。 UPLL专用于USB设备，MPLL用于设置FCLK、HCLK、PLCK。\n LOCKTIME寄存器(LOCK TIME COUNT) MPLL启动后需要等待一段时间（Lock Time），使得其输出稳定。在这段时间内，FCLK停振，CPU停止工作。 S3C2410中，位[23:12]用于UPLL，位[11:0]用于MPLL，默认值为0x00FFFFFF S3C2440中，位[31:16]用于UPLL，位[15:0]用于MPLL，默认值为0xFFFFFFFF MPLLCON(Main PLL Control) 位[19:12]为MDIV，位[9:4]为PDIV，位[1:0]为SDIV 对于S3C2410，MPLL(FCLK) = (mFin)/(p2^s) 对于S3C2440，MPLL(FCLK) = (2mFin)/(p*2^s) 其中：m = MDIV + 8, p = PDIV + 2, s = SDIV, Fin为晶振频率12M。 CLKDIVN(CLOCK DIVIDER CONTROL) 用于设置FCLK、HCLK、PCLK S3C2440还需要设置CAMDIVN寄存器。  PWM定时器 S3C2410和S3C2440的定时器部件完全一样，共有5个16位定时器。 定时器部件的时钟源为PCLK，首先通过两个8位的预分频器降低频率，然后进入第二级分频器，它们输出5种频率的时钟：2分频、4分频、8分频、16分频或者外部时钟TCLK0/TCLK1。\n TCFG0(TIMER CONFIGURATION) 位[7:0]、位[15:8]分别被用于控制预分频器0、1。 经过预分频器出来的时钟频率为：PCLK/(Prescaler value + 1) TCFG1 分频器选择，定时器的工作频率 = PCLK/(Prescaler value + 1)/(divider value) 每4位设置一个定时器，0000 = 1/2, 0001 = 1/4, 0010 = 1/8, 0011 = 1/16, 01xx = External TCLK0/1 TCNTBn/TCMPBn(COUNT BUFFER REGISTER \u0026amp; COMPARE BUFFER REGISTER) 只用到位[15:0]，TCNTBn中保存定时器的初始计数值，TCMPBn中保存比较值。 没有TCMPB4，因为定时器4没有输出引脚。 TCNTOn(COUNT OBSERVATION) 通过读取TCNTOn可以得知内部的TCNTn TCON(TIMER CONTROL) [3:0],[11:8],[15:12],[19:16],[22:20] 位0：开启停止 0停止定时器，1开启定时器 位1：手动更新 0无用，1将TCNTBn/TCMPBn的值装入内部的TCNTn、TCMPn 位2：输出反转 0TOUT不反转，1反转 位3：自动加载 0不自动加载，1在定时器计数达到0时，将TCNTBn/TCMPBn自动装入 第一次使用定时器，要设置手动更新为1，下一次如还要设置这一位，需先清0.  WATCHDOG定时器 WATCHDOG定时器的8位预分频器将PCLK分频后，被再次分频得到4种频率：16分频、32分频、64分频、128分频。\n WTCON(WATCHDOG TIMER CONTROL) [15:8] 预分频系数 [5] 定时器启动 0停止，1启动 [4:3] 时钟选择 00 = 1/16, 01 = 1/32, 10 = 1/64, 11 = 1/128 ?[1] 中断使能 0禁止中断，1使能中断 [0] WATCHDOG功能，当定时器达到0时，0不输出复位信号，1输出复位信号 WTDAT(WATCHDOG TIMER DATA) WTDAT被用来决定WATCHDOG的超时周期，在定时器启动后，当计数达到0时，WTDAT的值会自动传入WTCNT。 WTCNT(WATCHDOG TIMER COUNT) 初始计数值  UART    UBRDIVn（UART BAUD RATE DIVISOR）设置波特率 ULCONn（UART LINE CONTROL）设置传输格式 UCONn（UART CONTROL)\nI2C    LCD    TFT LCD时序信号 一帧数据的时序：\n VSYNC 表示一帧的开始。 VSPW 表示VSYNC信号的脉冲宽度为（VSPW+1）个HSYNC信号周期。 VBPD VSYNC信号脉冲后，还要经过（VBPD+1）个HSYNC信号周期，有效的行数据才出现。（上边框） LINEVAL+1行有效数据 VFPD+1个无效的行。（下边框） 一行数据的时序： HSYNC 表示一行数据的开始 HSPW 表示HSYNC信号的脉冲宽度为（HSPW+1）个VCLK信号周期。 HBPD HSYNC信号脉冲后，还要经过（HBPD+1）个VCLK信号周期，有效的像素数据才出现。（左边框） HOZVAL+1个像素的有效数据 FPD+1个无效的像素。（右边框）  VCLK(Hz) = HCLK/[(CLKVAL+1) * 2] Frame Rate\nTFT LCD控制器中REGBANK的17个寄存器可以分为6种： LCDCON1 ~ LCDCON5 LCDSADDR1 ~ LCDSADDR3 设置帧内存的地址 TPAL 临时调色板寄存器，用于快速输出一帧单色图像 LCDINTPND, LCDSRCPND, LCDINTMSK 用于LCD中断 REDLUT, GREENLUT, BLUELUT, DITHMODE 专用于STN LCD TCONSEL 专用于SEC TFT LCD\nold param    Supervivi\u0026gt; param show Number of parameters: 9 name : hex integer ------------------------------------------------------------- mach_type : 0000030e 782 media_type : 00000003 3 boot_mem_base : 30000000 805306368 baudrate : 0001c200 115200 xmodem : 00000001 1 xmodem_one_nak : 00000000 0 xmodem_initial_timeout : 000493e0 300000 xmodem_timeout : 000f4240 1000000 boot_delay : 01000000 16777216 Linux command line: noinitrd root=/dev/mtdblock2 init=/linuxrc console=ttySAC0  old part    Supervivi\u0026gt; part show Number of partitions: 5 name : offset size flag ------------------------------------------------------------ vivi : 0x00000000 0x00020000 0 eboot : 0x00020000 0x00020000 0 param : 0x00040000 0x00010000 0 kernel : 0x00050000 0x00200000 0 root : 0x00250000 0x03dac000 0 Supervivi\u0026gt; bon part info BON Partition Information Number of parttiton: 3 part0: offset = 0 size = 327680 bad_block = 0 part1: offset = 327680 size = 2097152 bad_block = 0 part2: offset = 2424832 size = 64667648 bad_block = 0  new param    Supervivi\u0026gt; param show Number of parameters: 9 name : hex integer ------------------------------------------------------------- mach_type : 0000016a 362 media_type : 00000003 3 boot_mem_base : 30000000 805306368 baudrate : 0001c200 115200 xmodem : 00000001 1 xmodem_one_nak : 00000000 0 xmodem_initial_timeout : 000493e0 300000 xmodem_timeout : 000f4240 1000000 boot_delay : 01000000 16777216 Linux command line: noinitrd root=/dev/mtdblock2 init=/linuxrc console=ttySAC0  new part    Supervivi\u0026gt; part show Number of partitions: 5 name : offset size flag ------------------------------------------------------------ vivi : 0x00000000 0x00020000 0 eboot : 0x00020000 0x00020000 0 param : 0x00040000 0x00010000 0 kernel : 0x00050000 0x00400000 0 root : 0x00450000 0x03bac000 0 Supervivi\u0026gt; bon part info BON Partition Information Number of parttiton: 3 part0: offset = 0 size = 327680 bad_block = 0 part1: offset = 327680 size = 4194304 bad_block = 0 part2: offset = 4521984 size = 62570496 bad_block = 0   重新安装QQ2440    第一步：通过Jlink烧写uboot或vivi    speed 12000 r #reset loadbin e:\\init.bin 0 setpc 0 g h loadbin e:\\u-boot.bin 0x33f80000 setpc 0x33f80000 g h loadbin e:\\supervivi 0x30000000 g  在u-boot中执行\nnand erase 0 30000 nand write.jffs2 30000000 0 30000 reboot  第二步：重新分区和格式化nand      nand分区 bon part 0 320k 4416k\n Supervivi\u0026gt; bon part info BON Partition Information Number of parttiton: 3 part0: offset = 0 size = 327680 bad_block = 0 part1: offset = 327680 size = 4194304 bad_block = 0 part2: offset = 4521984 size = 62570496 bad_block = 0    load flash vivi u\nreset\n  bon\n part del root part del kernel part add kernel 0x00050000 0x00400000 0 part add root 0x00450000 0x03bac000 0 part save Supervivi\u0026gt; part show Number of partitions: 5 name : offset size flag ------------------------------------------------------------ vivi : 0x00000000 0x00020000 0 eboot : 0x00020000 0x00020000 0 param : 0x00040000 0x00010000 0 kernel : 0x00050000 0x00400000 0 root : 0x00450000 0x03bac000 0 param set mach_type 362 param save reboot    第三步：烧写Linux内核和文件系统    load flash kernel u loadyaffs root u  在windows下使用SuperVivi-Transfer-Tool-Complete代替DNW Mac下使用DNW2\n连接线：    正品优越者 Y-105 USB转RS232串口连接转换线 1.5米 jlink V8仿真器 j-link ARM9 STM32 ARM仿真器\nparam set linux_cmd_line \u0026ldquo;noinitrd root=/dev/mtdblock3 init=/linuxrc console=ttySAC0,115200n8 debug\u0026rdquo;\nparam set linux_cmd_line \u0026ldquo;noinitrd root=/dev/mtdblock3 rootfstype=jffs2 init=/linuxrc console=ttySAC0,115200n8 debug\u0026rdquo;\nparam set linux_cmd_line \u0026ldquo;noinitrd console=ttySAC0,115200n8 init=/linuxrc root=/dev/nfs nfsroot=192.168.1.133:/home/woody/LHQ/nfs/root_default,proto=tcp,nfsvers=3,nolock ip=192.168.1.230:192.168.1.133:192.168.1.1:255.255.255.0:m:eth0:off\u0026rdquo;\nparam set linux_cmd_line \u0026ldquo;noinitrd console=ttySAC0,115200n8 init=/linuxrc root=/dev/nfs nfsroot=192.168.1.117:/Users/Woody/nfsroot/2440,proto=tcp,nfsvers=3,rsize=8192,wsize=8192,nolock ip=192.168.1.230:192.168.1.117:192.168.1.1:255.255.255.0:m:eth0:off\u0026rdquo;\n/home/woody/LHQ/src/build/uboot/2016.08.arm4vt/tools/mkimage -A arm -O linux -T kernel -C none -a 30008000 -e 30008000 -n linux-3.18.38 -d ./arch/arm/boot/zImage ./arch/arm/boot/uImage rm -r null\nlinux 3.18.38    Cross Compiler : arm-none-eabi 4.9.3 20150529 @Mac OS X EI Captitan 10.11.6 Configurations : mini2440_defconfig +yaffs2 +cs8900a\n  command line parameter:\n  param set mach_type 1999\n  ? bootloader 不能传递命令行参数到内核\nLinux 4.4.16    Cross Compiler : arm-none-eabi 4.9.3 20150529 @Mac OS X EI Captitan 10.11.6 Configurations : mini2440_defconfig +yaffs2 +cs8900a\n"},{"id":30,"href":"/tags/","title":"Tags","parent":"","content":""},{"id":31,"href":"/02-%E5%BC%80%E5%8F%91%E5%B7%A5%E5%85%B7/Vim/","title":"Vim","parent":"02 开发工具","content":"Vim    ^ 行首 $ 行尾 0 第一个字符\ngg 文件头 G 文件尾\n"}]